<?xml version="1.0" encoding="UTF-8"?>
<GeteBayDetailsResponse xmlns="urn:ebay:apis:eBLBaseComponents"><Timestamp>2010-07-13T11:48:08.242Z</Timestamp><Ack>Success</Ack><Version>675</Version><Build>E675_INTL_BUNDLED_11520936_R1</Build><ShippingServiceDetails><Description>只限本地收件</Description><ShippingService>HK_LocalPickUpOnly</ShippingService><ShippingServiceID>20101</ShippingServiceID><ServiceType>Flat</ServiceType><ValidForSellingFlow>true</ValidForSellingFlow><DetailVersion>1</DetailVersion><UpdateTime>2009-07-12T18:58:45.000Z</UpdateTime></ShippingServiceDetails><ShippingServiceDetails><Description>海外普通郵遞</Description><InternationalService>true</InternationalService><ShippingService>HK_InternationalRegularShipping</ShippingService><ShippingServiceID>70101</ShippingServiceID><ServiceType>Flat</ServiceType><ValidForSellingFlow>true</ValidForSellingFlow><DetailVersion>1</DetailVersion><UpdateTime>2009-07-12T18:58:45.000Z</UpdateTime></ShippingServiceDetails><ShippingServiceDetails><Description>本地郵政速遞</Description><ShippingService>HK_LocalCourier</ShippingService><ShippingServiceID>20102</ShippingServiceID><ServiceType>Flat</ServiceType><ValidForSellingFlow>true</ValidForSellingFlow><DetailVersion>1</DetailVersion><UpdateTime>2009-07-12T18:58:45.000Z</UpdateTime></ShippingServiceDetails><ShippingServiceDetails><Description>海外特許郵遞</Description><InternationalService>true</InternationalService><ShippingService>HK_InternationalSpecialShipping</ShippingService><ShippingServiceID>70102</ShippingServiceID><ServiceType>Flat</ServiceType><ValidForSellingFlow>true</ValidForSellingFlow><DetailVersion>1</DetailVersion><UpdateTime>2009-07-12T18:58:45.000Z</UpdateTime></ShippingServiceDetails><ShippingServiceDetails><Description>本地普通郵遞</Description><ShippingService>HK_DomesticRegularShipping</ShippingService><ShippingServiceID>20103</ShippingServiceID><ServiceType>Flat</ServiceType><ValidForSellingFlow>true</ValidForSellingFlow><DetailVersion>1</DetailVersion><UpdateTime>2009-07-12T18:58:45.000Z</UpdateTime></ShippingServiceDetails><ShippingServiceDetails><Description>本地特許郵遞</Description><ShippingService>HK_DomesticSpecialShipping</ShippingService><ShippingServiceID>20104</ShippingServiceID><ServiceType>Flat</ServiceType><ValidForSellingFlow>true</ValidForSellingFlow><DetailVersion>1</DetailVersion><UpdateTime>2009-07-12T18:58:45.000Z</UpdateTime></ShippingServiceDetails><ShippingServiceDetails><Description>運送優惠</Description><InternationalService>true</InternationalService><ShippingService>PromotionalShippingMethod</ShippingService><ShippingServiceID>70199</ShippingServiceID><ServiceType>Flat</ServiceType><ServiceType>Calculated</ServiceType><DetailVersion>1</DetailVersion><UpdateTime>2009-07-12T18:58:45.000Z</UpdateTime></ShippingServiceDetails><ShippingServiceDetails><Description>運送優惠</Description><ShippingService>PromotionalShippingMethod</ShippingService><ShippingServiceID>20199</ShippingServiceID><ServiceType>Flat</ServiceType><ServiceType>Calculated</ServiceType><DetailVersion>1</DetailVersion><UpdateTime>2009-07-12T18:58:45.000Z</UpdateTime></ShippingServiceDetails><UpdateTime>2009-07-12T18:58:45.000Z</UpdateTime></GeteBayDetailsResponse>